game_control/__init__.py
game_control/task_details.py
game_control/task_explore.py
game_control/task_logic.py
game_control/dungeon/__init__.py
game_control/dungeon/task_a_star.py
game_control/dungeon/task_dungeons_team.py
game_control/dungeon/task_dungeonsv2.py
game_control/dungeon/task_find_way.py
game_control/dungeon/task_reward_dungeons.py
game_control/dungeon/task_reward_dungeonsv2.py
game_control/role/__init__.py
game_control/role/gray_color.py
game_control/role/task_equip_enhanced.py
game_control/role/task_equip_enhanced_v2.py
game_control/role/task_equip_enhanced_v3.py
game_control/role/task_equip_upgrade.py
game_control/role/task_game_set.py
game_control/role/task_pet.py
game_control/role/task_skill_config.py
game_control/role/task_skills_learning.py
game_control/role/task_welfare.py
game_control/task/__init__.py
game_control/task/task_camp.py
game_control/task/task_main.py
game_control/task/task_reward.py
game_control/task/task_spur.py
otauto/__init__.py
otauto/a_star_v1.py
otauto/a_star_v2.py
otauto/background_color_v1.py
otauto/clent_ppocr.py
otauto/clent_yolov5.py
otauto/coordinate_conversion.py
otauto/coordinate_converter.py
otauto/data_cleansing.py
otauto/data_interface.py
otauto/data_interfacev1.py
otauto/dict_op.py
otauto/docker_fdv1.py
otauto/helper_functions.py
otauto/http_client.py
otauto/image_matcher.py
otauto/image_processing.py
otauto/image_traits.py
otauto/imagefinder_v2.py
otauto/imagefinder_v3.py
otauto/imagefinder_v4.py
otauto/ini_file_operationv2.py
otauto/log.py
otauto/mongodb_v2.py
otauto/monochrome_search_v2.py
otauto/multipoint_colors_v4.py
otauto/multipoint_colors_v5.py
otauto/myemail.py
otauto/myemailv2.py
otauto/ocrv4_grpc_client.py
otauto/redis_main.py
otauto/shan_client.py
otauto/shan_clientv1.py
otauto/template_match_mt.py
otauto/text_correctionv1.py
otauto/text_correctionv2.py
otauto/vnc_recognition.py
otauto/vnc_recognitionv1.py
otauto/way_finding.py
otauto/yolov5_grpc_client.py
otauto/opencv_image/__init__.py
otauto-0.7.6.dist-info/METADATA
otauto-0.7.6.dist-info/WHEEL
otauto-0.7.6.dist-info/top_level.txt
otauto-0.7.6.dist-info/RECORD
